tidyspss/__init__.py
tidyspss/processor.py
tidyspss-0.2.0.dist-info/WHEEL
tidyspss-0.2.0.dist-info/entry_points.txt
tidyspss-0.2.0.dist-info/METADATA
tidyspss-0.2.0.dist-info/RECORD
