Metadata-Version: 2.3
Name: tidyspss
Version: 0.2.0
Summary: A Python package for quick processing and transforming SPSS files
Keywords: spss,sav,data,processing,pandas,pyreadstat
Author: Albert Li
Requires-Dist: openpyxl>=3.0.0
Requires-Dist: pandas>=2.3.0
Requires-Dist: polars>=1.31.0
Requires-Dist: pyreadstat>=1.3.0
Requires-Python: >=3.11
